performant/__init__.py
performant/tools.py
performant_babe269-0.0.3.dist-info/LICENSE
performant_babe269-0.0.3.dist-info/METADATA
performant_babe269-0.0.3.dist-info/WHEEL
performant_babe269-0.0.3.dist-info/top_level.txt
performant_babe269-0.0.3.dist-info/RECORD
