Metadata-Version: 2.1
Name: performant-babe269
Version: 0.0.3
Summary: A toolset for easy formant extraction and visualization from wav files and TTS models
Home-page: https://github.com/babe269/formant-tools
Author: Binu Abeysinghe
Author-email: babe269@aucklanduni.ac.nz
License: UNKNOWN
Project-URL: Bug Tracker, https://github.com/babe269/formant-tools/issues
Platform: UNKNOWN
Classifier: Programming Language :: Python :: 3
Classifier: License :: OSI Approved :: MIT License
Classifier: Operating System :: OS Independent
Requires-Python: >=3.6
License-File: LICENSE
